gify_plot/__init__.py
gify_plot/gify_plot.py
giphy_plot/__init__.py
giphy_plot/giphy_plot.py
gify_plot-0.0.14.dist-info/METADATA
gify_plot-0.0.14.dist-info/WHEEL
gify_plot-0.0.14.dist-info/top_level.txt
gify_plot-0.0.14.dist-info/RECORD
