Metadata-Version: 2.1
Name: gify-plot
Version: 0.0.14
Summary: A basic package to turn plots into gifs (currently in beta phase).
Home-page: https://github.com/FrancescoDiCursi/gify_plot
Author: Francesco Di Cursi
Author-email: f.dicursi@studenti.unipi.it
License: MIT
Keywords: gif,plot,seaborn,matplotlib,plotly
Platform: UNKNOWN
Classifier: Development Status :: 1 - Planning
Classifier: Intended Audience :: Developers
Classifier: Programming Language :: Python :: 3
Classifier: Operating System :: Unix
Classifier: Operating System :: MacOS :: MacOS X
Classifier: Operating System :: Microsoft :: Windows
Requires-Dist: pandas
Requires-Dist: tqdm
Requires-Dist: Pillow
Requires-Dist: matplotlib
Requires-Dist: seaborn
Requires-Dist: plotly
Requires-Dist: datetimerange
Requires-Dist: datetime
